shaper_bin-0.14.0.dist-info/licenses/LICENSE
shaper_pkg/__init__.py
shaper_pkg/cli.py
shaper_pkg/install.py
shaper_pkg/uninstall.py
shaper_pkg/bin/SHA256SUMS
shaper_bin-0.14.0.dist-info/METADATA
shaper_bin-0.14.0.dist-info/WHEEL
shaper_bin-0.14.0.dist-info/entry_points.txt
shaper_bin-0.14.0.dist-info/top_level.txt
shaper_bin-0.14.0.dist-info/RECORD
