Metadata-Version: 2.4
Name: shaper-bin
Version: 0.14.0
Summary: Minimal Embedded Analytics and Data Platform
Author-email: Taleshape <hi@taleshape.com>
License: MPL-2.0
Project-URL: Homepage, https://taleshape.com/shaper
Project-URL: Documentation, https://taleshape.com/shaper/docs/
Project-URL: Repository, https://github.com/taleshape-com/shaper
Project-URL: Issues, https://github.com/taleshape-com/shaper/issues
Keywords: data,analytics,dashboards,duckdb
Classifier: Development Status :: 4 - Beta
Classifier: Intended Audience :: Developers
Classifier: License :: OSI Approved :: Mozilla Public License 2.0 (MPL 2.0)
Classifier: Programming Language :: Python :: 3
Classifier: Programming Language :: Python :: 3.8
Classifier: Programming Language :: Python :: 3.9
Classifier: Programming Language :: Python :: 3.10
Classifier: Programming Language :: Python :: 3.11
Classifier: Programming Language :: Python :: 3.12
Requires-Python: >=3.8
License-File: LICENSE
Requires-Dist: requests>=2.31.0
Dynamic: license-file
